Makefile
README.rst
setup.py
docs/Makefile
docs/make.bat
docs/source/HISTORY.rst
docs/source/README.rst
docs/source/api.rst
docs/source/conf.py
docs/source/index.rst
scripts/api-sample.py
scripts/out.txt
scripts/sample.zip
xmldirector/__init__.py
xmldirector.twitter.egg-info/PKG-INFO
xmldirector.twitter.egg-info/SOURCES.txt
xmldirector.twitter.egg-info/dependency_links.txt
xmldirector.twitter.egg-info/entry_points.txt
xmldirector.twitter.egg-info/namespace_packages.txt
xmldirector.twitter.egg-info/not-zip-safe
xmldirector.twitter.egg-info/requires.txt
xmldirector.twitter.egg-info/top_level.txt
xmldirector/twitter/__init__.py
xmldirector/twitter/configure.zcml
xmldirector/twitter/header.txt
xmldirector/twitter/i18n.py
xmldirector/twitter/interfaces.py
xmldirector/twitter/logger.py
xmldirector/twitter/browser/__init__.py
xmldirector/twitter/browser/configure.zcml
xmldirector/twitter/browser/controlpanel.py
xmldirector/twitter/browser/twitter_authentication.pt
xmldirector/twitter/browser/twitter_authentication.py
xmldirector/twitter/locales/LC_MESSAGES/de/README.txt
xmldirector/twitter/profiles/default/README.txt
xmldirector/twitter/profiles/default/browserlayer.xml
xmldirector/twitter/profiles/default/controlpanel.xml
xmldirector/twitter/profiles/default/metadata.xml
xmldirector/twitter/profiles/default/registry.xml
xmldirector/twitter/profiles/default/types.xml
xmldirector/twitter/profiles/default/types/xmldirector.plonecore.connector.xml