Metadata-Version: 1.1
Name: xmldirector.twitter
Version: 0.2.0
Summary: Plone/XML-Director integration withTwitter
Home-page: http://pypi.python.org/pypi/xmldirector.twitter
Author: Andreas Jung
Author-email: info@zopyx.com
License: GPL
Keywords: xml-director twitter XML Plone Python
Platform: UNKNOWN
Classifier: Programming Language :: Python
Classifier: Framework :: Plone
Classifier: Framework :: Plone :: 4.3
Classifier: Framework :: Plone :: 5.0
Classifier: Framework :: Zope2
Classifier: Topic :: Software Development :: Libraries :: Python Modules
